aochelpers/__init__.py
aochelpers/bsearch.py
aochelpers/intify.py
aochelpers/mathematical.py
aochelpers/neighbors.py
aochelpers/read.py
flatypus_aochelpers-0.0.6.dist-info/LICENSE
flatypus_aochelpers-0.0.6.dist-info/METADATA
flatypus_aochelpers-0.0.6.dist-info/WHEEL
flatypus_aochelpers-0.0.6.dist-info/top_level.txt
flatypus_aochelpers-0.0.6.dist-info/RECORD
